pygamelab/__init__.py
pygamelab/canvas.py
pygamelab/common.py
pygamelab/data.py
pygamelab/document.py
pygamelab/locals.py
pygamelab/random.py
pygamelab/storage.py
PyGameLab-3.2.7.dist-info/LICENCE
PyGameLab-3.2.7.dist-info/METADATA
PyGameLab-3.2.7.dist-info/WHEEL
PyGameLab-3.2.7.dist-info/top_level.txt
PyGameLab-3.2.7.dist-info/RECORD
