Metadata-Version: 2.1
Name: PyGameLab
Version: 3.2.7
Summary: PyGameLab: A versatile Python library for game development using Pygame.
Author-email: Leandro Feippe <feippe5454@gmail.com>
Project-URL: Homepage, https://github.com/leandrofeippe/pygamelab
Project-URL: Bug Tracker, https://github.com/leandrofeippe/pygamelab/issues
Classifier: Programming Language :: Python :: 3
Classifier: License :: OSI Approved :: MIT License
Classifier: Operating System :: OS Independent
Requires-Python: >=3.7
License-File: LICENCE
